ecoact_geo/__init__.py
ecoact_geo/db_model/__init__.py
ecoact_geo/domain_model/__init__.py
ecoact_geo-0.0.1.dist-info/METADATA
ecoact_geo-0.0.1.dist-info/WHEEL
ecoact_geo-0.0.1.dist-info/RECORD
